[
  {
    "guid": "b677faf8584f",
    "title": "O Jardineiro que Deu Voz ao Vento | História Relaxante",
    "description": "Mergulhe na calma história de Arthur, um jardineiro que sentia a falta de uma canção em seu jardim perfeito.",
    "audio_url": "https://archive.org/download/plumanoturna-podcast/20260307_o-jardineiro-que-deu-voz-ao-vento-historia-relaxante.mp3",
    "image_url": "https://www.plumanoturna.com.br/podcast-cover.png",
    "duration": "01:00:00",
    "file_size": 57601088,
    "pub_date": "Sat, 07 Mar 2026 02:39:21 GMT"
  }
]